openkmi/__init__.py
openkmi/grid_data.py
openkmi/point_obs.py
openkmi-0.6.0.dist-info/LICENSE
openkmi-0.6.0.dist-info/METADATA
openkmi-0.6.0.dist-info/WHEEL
openkmi-0.6.0.dist-info/top_level.txt
openkmi-0.6.0.dist-info/RECORD
