Metadata-Version: 2.1
Name: openkmi
Version: 0.6.0
Summary: Python package to download open data from KMI
Home-page: https://github.com/TimFranken/openkmi
Author: Tim Franken
Author-email: tim.franken@sumaqua.be
License: mit
Project-URL: Documentation, https://github.com/TimFranken/openkmi/tree/master/examples
Classifier: Development Status :: 3 - Alpha
Classifier: Programming Language :: Python :: 3
Classifier: License :: OSI Approved :: MIT License
Classifier: Operating System :: OS Independent
Classifier: Intended Audience :: Science/Research
Classifier: Intended Audience :: Developers
Requires-Python: >=3.6
License-File: LICENSE
Requires-Dist: pandas
Requires-Dist: owslib
